ZCore/__init__.py
pyZCore-0.0.1.dev1.dist-info/LICENSE
pyZCore-0.0.1.dev1.dist-info/METADATA
pyZCore-0.0.1.dev1.dist-info/WHEEL
pyZCore-0.0.1.dev1.dist-info/top_level.txt
pyZCore-0.0.1.dev1.dist-info/RECORD
