Metadata-Version: 2.1
Name: pyZCore
Version: 0.0.1.dev1
Summary: IP manager for ZCore Repository
Home-page: UNKNOWN
Author: Aduri Sri Sambasiva Advaith
Author-email: advaith.aduri@gmail.com
License: UNKNOWN
Project-URL: source, https://github.com/advaith-aduri/pyZCore/
Platform: UNKNOWN
Classifier: Programming Language :: Python :: 3
Classifier: License :: OSI Approved :: MIT License
Classifier: Operating System :: Unix
Requires-Python: >=3.6
License-File: LICENSE
